noop.cpython-311-darwin.so
sqlite_lines/__init__.py
sqlite_lines/lines0.dylib
sqlite_lines/version.py
sqlite_lines-0.2.2.dist-info/METADATA
sqlite_lines-0.2.2.dist-info/WHEEL
sqlite_lines-0.2.2.dist-info/top_level.txt
sqlite_lines-0.2.2.dist-info/RECORD
